d3m/uow/__init__.py
d3m/uow/abstractions.py
d3m/uow/py.typed
d3m/uow/uow.py
dddmisc_unit_of_work-0.3.2.dist-info/LICENSE
dddmisc_unit_of_work-0.3.2.dist-info/METADATA
dddmisc_unit_of_work-0.3.2.dist-info/WHEEL
dddmisc_unit_of_work-0.3.2.dist-info/RECORD
