Metadata-Version: 2.1
Name: dddmisc-unit-of-work
Version: 0.3.2
Summary: This package provides the implementation pattern 'unit of work'
Home-page: https://dddmisc.github.io/dddmisc-docs/
License: MIT
Author: Vladislav Vorobyov
Author-email: vladislav.vorobyov@gmail.com
Requires-Python: >=3.10,<4.0
Classifier: License :: OSI Approved :: MIT License
Classifier: Programming Language :: Python :: 3
Classifier: Programming Language :: Python :: 3.10
Classifier: Programming Language :: Python :: 3.11
Classifier: Programming Language :: Python :: 3.12
Requires-Dist: dddmisc-core (>=0.7.0,<0.8.0)
Project-URL: Repository, https://github.com/dddmisc/dddmisc
